DESCRIPTION
MANIFEST.in
README
README.rst
setup.py
feedback/__init__.py
feedback/admin.py
feedback/forms.py
feedback/models.py
feedback/settings.py
feedback/urls.py
feedback/utils.py
feedback/views.py
feedback/locale/ru/LC_MESSAGES/django.mo
feedback/locale/ru/LC_MESSAGES/django.po
feedback/migrations/0001_initial.py
feedback/migrations/0002_auto__del_response__del_responseattachments__add_mailinglist__add_feed.py
feedback/migrations/__init__.py
feedback/redsolution_setup/__init__.py
feedback/redsolution_setup/admin.py
feedback/redsolution_setup/make.py
feedback/redsolution_setup/models.py
feedback/redsolution_setup/urls.py
feedback/redsolution_setup/views.py
feedback/static/feedback/js/feedback.js
feedback/templates/feedback/feedback.html
feedback/templates/feedback/feedback_message.txt
feedback/templates/feedback/feedback_page.html
feedback/templates/feedback/thankyou.html
feedback/templatetags/__init__.py
feedback/templatetags/feedback_tags.py
redsolutioncms.django_simple_feedback.egg-info/PKG-INFO
redsolutioncms.django_simple_feedback.egg-info/SOURCES.txt
redsolutioncms.django_simple_feedback.egg-info/dependency_links.txt
redsolutioncms.django_simple_feedback.egg-info/entry_points.txt
redsolutioncms.django_simple_feedback.egg-info/not-zip-safe
redsolutioncms.django_simple_feedback.egg-info/requires.txt
redsolutioncms.django_simple_feedback.egg-info/top_level.txt